dune_gdt_tutorials/__init__.py
dune_gdt_tutorials/version.py
dune_gdt_tutorials-0.post2.dev17.dist-info/LICENSE.txt
dune_gdt_tutorials-0.post2.dev17.dist-info/METADATA
dune_gdt_tutorials-0.post2.dev17.dist-info/WHEEL
dune_gdt_tutorials-0.post2.dev17.dist-info/entry_points.txt
dune_gdt_tutorials-0.post2.dev17.dist-info/top_level.txt
dune_gdt_tutorials-0.post2.dev17.dist-info/RECORD
