Metadata-Version: 2.1
Name: dune-gdt-tutorials
Version: 0.post2.dev17
Summary: 
Home-page: https://zivgitlab.uni-muenster.de/ag-ohlberger/dune-community/dune-gdt-tutorials/
Author: dune-gdt developers
Author-email: main.developers@pymor.org
Maintainer: Rene Fritze
Maintainer-email: rene.fritze@wwu.de
License: LICENSE.txt
Platform: UNKNOWN
Classifier: Development Status :: 4 - Beta
Classifier: License :: OSI Approved :: BSD License
Classifier: Programming Language :: Python :: 3.7
Classifier: Programming Language :: Python :: 3.8
Classifier: Programming Language :: Python :: 3.9
Classifier: Intended Audience :: Science/Research
Classifier: Topic :: Scientific/Engineering :: Mathematics
Requires-Python: >=3.7
License-File: LICENSE.txt
Requires-Dist: dune-gdt (~=2021.1)
Requires-Dist: dune-xt (~=2021.1)
Requires-Dist: sphinx
Requires-Dist: myst-nb
